[
    {
        "dno": 456331,
        "title": "TITLE 001",
        "data": [
            {
                "datetime": "2022-01-01",
                "data":35
            },
            {
                "datetime": "2022-01-02",
                "data":34
            },
            {
                "datetime": "2022-01-03",
                "data":32
            },
            {
                "datetime": "2022-01-04",
                "data":30
            },
            {
                "datetime": "2022-01-05",
                "data":31
            },
            {
                "datetime": "2022-01-06",
                "data":30
            },
            {
                "datetime": "2022-01-07",
                "data":33
            },
            {
                "datetime": "2022-01-08",
                "data":35
            },
            {
                "datetime": "2022-01-09",
                "data":34
            },
            {
                "datetime": "2022-01-10",
                "data":32
            }
        ]
    },
    {
        "dno": 456728,
        "title": "TITLE 002",
        "data": [
            {
                "datetime": "2022-01-01",
                "data":28
            },
            {
                "datetime": "2022-01-02",
                "data":24
            },
            {
                "datetime": "2022-01-03",
                "data":25
            },
            {
                "datetime": "2022-01-04",
                "data":21
            },
            {
                "datetime": "2022-01-05",
                "data":26
            },
            {
                "datetime": "2022-01-06",
                "data":25
            },
            {
                "datetime": "2022-01-07",
                "data":26
            },
            {
                "datetime": "2022-01-08",
                "data":22
            },
            {
                "datetime": "2022-01-09",
                "data":27
            },
            {
                "datetime": "2022-01-10",
                "data":25
            }
        ]
    },
    {
        "dno": 454322,
        "title": "TITLE 003",
        "data": [
            {
                "datetime": "2022-01-01",
                "data":25
            },
            {
                "datetime": "2022-01-02",
                "data":27
            },
            {
                "datetime": "2022-01-03",
                "data":26
            },
            {
                "datetime": "2022-01-04",
                "data":28
            },
            {
                "datetime": "2022-01-05",
                "data":25
            },
            {
                "datetime": "2022-01-06",
                "data":26
            },
            {
                "datetime": "2022-01-07",
                "data":27
            },
            {
                "datetime": "2022-01-08",
                "data":24
            },
            {
                "datetime": "2022-01-09",
                "data":26
            },
            {
                "datetime": "2022-01-10",
                "data":28
            }
        ]
    },
    {
        "dno": 457242,
        "title": "TITLE 003",
        "data": [
            {
                "datetime": "2022-01-01",
                "data":25
            },
            {
                "datetime": "2022-01-02",
                "data":27
            },
            {
                "datetime": "2022-01-03",
                "data":26
            },
            {
                "datetime": "2022-01-04",
                "data":28
            },
            {
                "datetime": "2022-01-05",
                "data":25
            },
            {
                "datetime": "2022-01-06",
                "data":26
            },
            {
                "datetime": "2022-01-07",
                "data":27
            },
            {
                "datetime": "2022-01-08",
                "data":24
            },
            {
                "datetime": "2022-01-09",
                "data":26
            },
            {
                "datetime": "2022-01-10",
                "data":28
            }
        ]
    }
]